django_sivumedia.py
django_sivumedia-0.1.1.dist-info/METADATA
django_sivumedia-0.1.1.dist-info/WHEEL
django_sivumedia-0.1.1.dist-info/historia.json
django_sivumedia-0.1.1.dist-info/top_level.txt
django_sivumedia-0.1.1.dist-info/RECORD
