Metadata-Version: 2.4
Name: django-sivumedia
Version: 0.1.1
Summary: Django-sivumediatoteutus
Author-email: Antti Hautaniemi <antti.hautaniemi@pispalanit.fi>
Project-URL: Repository, https://github.com/an7oine/django-sivumedia.git
Requires-Python: >=3.8
